{
  "schema_version": "1.0.0",
  "command": "cpack",
  "description": "CPACK(1) CMake CPACK(1)",
  "global_flags": [
    {
      "short": null,
      "long": "--config",
      "value_type": "Bool",
      "takes_value": false,
      "description": "By default, CPackConfig.cmake in the  current  direc‐ tory will be used.",
      "multiple": false,
      "conflicts_with": [],
      "requires": []
    },
    {
      "short": null,
      "long": "--debug",
      "value_type": "Bool",
      "takes_value": false,
      "description": "This option is intended mainly for the developers of cpack itself and is not normally needed by project developers.",
      "multiple": false,
      "conflicts_with": [],
      "requires": []
    },
    {
      "short": "-h",
      "long": "--help",
      "value_type": "Bool",
      "takes_value": false,
      "description": null,
      "multiple": false,
      "conflicts_with": [],
      "requires": []
    },
    {
      "short": null,
      "long": "--help-command",
      "value_type": "Bool",
      "takes_value": false,
      "description": null,
      "multiple": false,
      "conflicts_with": [],
      "requires": []
    },
    {
      "short": null,
      "long": "--help-command-list",
      "value_type": "Bool",
      "takes_value": false,
      "description": null,
      "multiple": false,
      "conflicts_with": [],
      "requires": []
    },
    {
      "short": null,
      "long": "--help-commands",
      "value_type": "Bool",
      "takes_value": false,
      "description": null,
      "multiple": false,
      "conflicts_with": [],
      "requires": []
    },
    {
      "short": null,
      "long": "--help-full",
      "value_type": "Bool",
      "takes_value": false,
      "description": null,
      "multiple": false,
      "conflicts_with": [],
      "requires": []
    },
    {
      "short": null,
      "long": "--help-manual",
      "value_type": "Bool",
      "takes_value": false,
      "description": null,
      "multiple": false,
      "conflicts_with": [],
      "requires": []
    },
    {
      "short": null,
      "long": "--help-manual-list",
      "value_type": "Bool",
      "takes_value": false,
      "description": null,
      "multiple": false,
      "conflicts_with": [],
      "requires": []
    },
    {
      "short": null,
      "long": "--help-module",
      "value_type": "Bool",
      "takes_value": false,
      "description": null,
      "multiple": false,
      "conflicts_with": [],
      "requires": []
    },
    {
      "short": null,
      "long": "--help-module-list",
      "value_type": "Bool",
      "takes_value": false,
      "description": null,
      "multiple": false,
      "conflicts_with": [],
      "requires": []
    },
    {
      "short": null,
      "long": "--help-modules",
      "value_type": "Bool",
      "takes_value": false,
      "description": null,
      "multiple": false,
      "conflicts_with": [],
      "requires": []
    },
    {
      "short": null,
      "long": "--help-policies",
      "value_type": "Bool",
      "takes_value": false,
      "description": null,
      "multiple": false,
      "conflicts_with": [],
      "requires": []
    },
    {
      "short": null,
      "long": "--help-policy",
      "value_type": "Bool",
      "takes_value": false,
      "description": null,
      "multiple": false,
      "conflicts_with": [],
      "requires": []
    },
    {
      "short": null,
      "long": "--help-policy-list",
      "value_type": "Bool",
      "takes_value": false,
      "description": null,
      "multiple": false,
      "conflicts_with": [],
      "requires": []
    },
    {
      "short": null,
      "long": "--help-properties",
      "value_type": "Bool",
      "takes_value": false,
      "description": null,
      "multiple": false,
      "conflicts_with": [],
      "requires": []
    },
    {
      "short": null,
      "long": "--help-property",
      "value_type": "Bool",
      "takes_value": false,
      "description": null,
      "multiple": false,
      "conflicts_with": [],
      "requires": []
    },
    {
      "short": null,
      "long": "--help-property-list",
      "value_type": "Bool",
      "takes_value": false,
      "description": null,
      "multiple": false,
      "conflicts_with": [],
      "requires": []
    },
    {
      "short": null,
      "long": "--help-variable",
      "value_type": "Bool",
      "takes_value": false,
      "description": null,
      "multiple": false,
      "conflicts_with": [],
      "requires": []
    },
    {
      "short": null,
      "long": "--help-variable-list",
      "value_type": "Bool",
      "takes_value": false,
      "description": null,
      "multiple": false,
      "conflicts_with": [],
      "requires": []
    },
    {
      "short": null,
      "long": "--help-variables",
      "value_type": "Bool",
      "takes_value": false,
      "description": null,
      "multiple": false,
      "conflicts_with": [],
      "requires": []
    },
    {
      "short": null,
      "long": "--list-presets",
      "value_type": "Bool",
      "takes_value": false,
      "description": null,
      "multiple": false,
      "conflicts_with": [],
      "requires": []
    },
    {
      "short": null,
      "long": "--preset",
      "value_type": "Bool",
      "takes_value": false,
      "description": null,
      "multiple": false,
      "conflicts_with": [],
      "requires": []
    },
    {
      "short": null,
      "long": "--trace",
      "value_type": "Bool",
      "takes_value": false,
      "description": null,
      "multiple": false,
      "conflicts_with": [],
      "requires": []
    },
    {
      "short": null,
      "long": "--trace-expand",
      "value_type": "Bool",
      "takes_value": false,
      "description": null,
      "multiple": false,
      "conflicts_with": [],
      "requires": []
    },
    {
      "short": null,
      "long": "--vendor",
      "value_type": "Bool",
      "takes_value": false,
      "description": null,
      "multiple": false,
      "conflicts_with": [],
      "requires": []
    },
    {
      "short": "-V",
      "long": "--verbose",
      "value_type": "Bool",
      "takes_value": false,
      "description": "cpack  with verbose output.  This can be used to show more details from the package generation tools and is suitable for project developers.",
      "multiple": false,
      "conflicts_with": [],
      "requires": []
    },
    {
      "short": "-version",
      "long": "--version",
      "value_type": "Bool",
      "takes_value": false,
      "description": "The output is printed to a named <file> if given.",
      "multiple": false,
      "conflicts_with": [],
      "requires": []
    },
    {
      "short": "-B",
      "long": null,
      "value_type": "Directory",
      "takes_value": true,
      "description": "CPACK_PACKAGE_DIRECTORY,  which  controls  the directory where CPack will perform its packaging work.  The resultant package(s) will be created at this location by default and a _CPack_Packages subdirectory will also be created below  this  directory to use as a working area during package creation.",
      "multiple": false,
      "conflicts_with": [],
      "requires": []
    },
    {
      "short": "-C",
      "long": null,
      "value_type": "String",
      "takes_value": true,
      "description": "When the  CMake  project  uses  a  multi-configuration generator such as Xcode or Visual Studio, this option is needed to tell cpack which built executables to include in the package.  The user is responsible for ensuring that the configuration(s) listed have already been built before invoking cpack.",
      "multiple": false,
      "conflicts_with": [],
      "requires": []
    },
    {
      "short": "-D",
      "long": null,
      "value_type": "File",
      "takes_value": true,
      "description": "This will override any value set for <var> in the input file read by cpack.",
      "multiple": false,
      "conflicts_with": [],
      "requires": []
    },
    {
      "short": "-G",
      "long": null,
      "value_type": "File",
      "takes_value": true,
      "description": "is  a semicolon-separated list of generator names.  cpack will iterate through this list and produce package(s) in that generator's format according to the details provided in the CPackConfig.cmake configuration file.  If this option is not  given,  the CPACK_GENERATOR variable determines the default set of generators that will be used.",
      "multiple": false,
      "conflicts_with": [],
      "requires": []
    },
    {
      "short": "-G.",
      "long": null,
      "value_type": "Bool",
      "takes_value": false,
      "description": null,
      "multiple": false,
      "conflicts_with": [],
      "requires": []
    },
    {
      "short": "-P",
      "long": null,
      "value_type": "File",
      "takes_value": true,
      "description": "Any value set for this variable  in  the  CPackCon‐ fig.cmake file will then be ignored.",
      "multiple": false,
      "conflicts_with": [],
      "requires": []
    },
    {
      "short": "-R",
      "long": null,
      "value_type": "File",
      "takes_value": true,
      "description": "the  value  of the CPACK_PACKAGE_VERSION variable used for packaging.  It will override a value set in the CPackCon‐ fig.cmake   file   or   one   automatically    computed    from    CPACK_PACKAGE_VERSION_MAJOR,    CPACK_PACKAGE_VERSION_MINOR    and CPACK_PACKAGE_VERSION_PATCH.",
      "multiple": false,
      "conflicts_with": [],
      "requires": []
    }
  ],
  "subcommands": [],
  "positional": [],
  "source": "ManPage",
  "confidence": 0.8,
  "version": null
}