{
  "schema_version": "1.0.0",
  "command": "debconf-apt-progress",
  "description": "debconf-apt-progress - install packages using debconf to display a",
  "global_flags": [
    {
      "short": null,
      "long": "--config",
      "value_type": "Bool",
      "takes_value": false,
      "description": "environment  variables  necessary to start up a progress bar frontend.",
      "multiple": false,
      "conflicts_with": [],
      "requires": []
    },
    {
      "short": null,
      "long": "--dlwaypoint",
      "value_type": "Bool",
      "takes_value": false,
      "description": "what  percent  of  the progress bar to use for downloading packages.  The remainder will be used for installing packages.  The default  is  to  use  15% for downloading and the remaining 85% for installing.",
      "multiple": false,
      "conflicts_with": [],
      "requires": []
    },
    {
      "short": null,
      "long": "--from",
      "value_type": "Bool",
      "takes_value": false,
      "description": null,
      "multiple": false,
      "conflicts_with": [],
      "requires": []
    },
    {
      "short": null,
      "long": "--logfile",
      "value_type": "Bool",
      "takes_value": false,
      "description": null,
      "multiple": false,
      "conflicts_with": [],
      "requires": []
    },
    {
      "short": null,
      "long": "--logstderr",
      "value_type": "Bool",
      "takes_value": false,
      "description": "you  supply  neither",
      "multiple": false,
      "conflicts_with": [],
      "requires": []
    },
    {
      "short": null,
      "long": "--no-progress",
      "value_type": "Bool",
      "takes_value": false,
      "description": "starting,  stopping,  or stepping the progress bar. Progress messages from apt, media change events, and debconf questions  will still be passed through to debconf.",
      "multiple": false,
      "conflicts_with": [],
      "requires": []
    },
    {
      "short": null,
      "long": "--start",
      "value_type": "Bool",
      "takes_value": false,
      "description": "to  100  by  default.  Use",
      "multiple": false,
      "conflicts_with": [],
      "requires": []
    },
    {
      "short": null,
      "long": "--stop",
      "value_type": "Bool",
      "takes_value": false,
      "description": null,
      "multiple": false,
      "conflicts_with": [],
      "requires": []
    },
    {
      "short": null,
      "long": "--to",
      "value_type": "Bool",
      "takes_value": false,
      "description": "used with --start, make the progress bar end at waypoint rather than 100.",
      "multiple": false,
      "conflicts_with": [],
      "requires": []
    }
  ],
  "subcommands": [],
  "positional": [],
  "source": "ManPage",
  "confidence": 0.8,
  "version": null
}