{
  "schema_version": "1.0.0",
  "command": "git-upload-pack",
  "description": "git-upload-pack - Send objects packed back to git-fetch-pack",
  "global_flags": [
    {
      "short": null,
      "long": "--advertise-refs",
      "value_type": "Directory",
      "takes_value": true,
      "description": null,
      "multiple": false,
      "conflicts_with": [],
      "requires": []
    },
    {
      "short": null,
      "long": "--http-backend-info-refs",
      "value_type": "String",
      "takes_value": true,
      "description": null,
      "multiple": false,
      "conflicts_with": [],
      "requires": []
    },
    {
      "short": null,
      "long": "--stateless-rpc",
      "value_type": "String",
      "takes_value": true,
      "description": null,
      "multiple": false,
      "conflicts_with": [],
      "requires": []
    },
    {
      "short": null,
      "long": "--strict",
      "value_type": "Bool",
      "takes_value": false,
      "description": null,
      "multiple": false,
      "conflicts_with": [],
      "requires": []
    },
    {
      "short": null,
      "long": "--timeout",
      "value_type": "String",
      "takes_value": true,
      "description": null,
      "multiple": false,
      "conflicts_with": [],
      "requires": []
    }
  ],
  "subcommands": [],
  "positional": [
    {
      "name": "directory",
      "value_type": "Directory",
      "required": true,
      "multiple": false,
      "description": null
    }
  ],
  "source": "Merged",
  "confidence": 0.9,
  "version": null
}