{
  "schema_version": "1.0.0",
  "command": "gprofng",
  "description": "gprofng - The next generation GNU application profiling tool",
  "global_flags": [
    {
      "short": null,
      "long": "--check",
      "value_type": "Bool",
      "takes_value": false,
      "description": "verify if the hardware and software environment is supported.",
      "multiple": false,
      "conflicts_with": [],
      "requires": []
    },
    {
      "short": null,
      "long": "--help",
      "value_type": "Bool",
      "takes_value": false,
      "description": "print usage information and exit.",
      "multiple": false,
      "conflicts_with": [],
      "requires": []
    },
    {
      "short": null,
      "long": "--verbose",
      "value_type": "Bool",
      "takes_value": false,
      "description": "enable (on) or disable (off) verbose mode; the default is \"off\".",
      "multiple": false,
      "conflicts_with": [],
      "requires": []
    },
    {
      "short": null,
      "long": "--version",
      "value_type": "Bool",
      "takes_value": false,
      "description": "print the version number and exit.",
      "multiple": false,
      "conflicts_with": [],
      "requires": []
    }
  ],
  "subcommands": [
    {
      "name": "action",
      "description": null,
      "flags": [],
      "positional": [],
      "subcommands": [],
      "aliases": []
    },
    {
      "name": "archive",
      "description": "include binaries and source code in an experiment directory.",
      "flags": [
        {
          "short": null,
          "long": "--help",
          "value_type": "Bool",
          "takes_value": false,
          "description": "print usage information and exit.",
          "multiple": false,
          "conflicts_with": [],
          "requires": []
        },
        {
          "short": null,
          "long": "--verbose",
          "value_type": "Bool",
          "takes_value": false,
          "description": "enable (on) or disable (off) verbose mode; the default is \"off\".",
          "multiple": false,
          "conflicts_with": [],
          "requires": []
        },
        {
          "short": null,
          "long": "--version",
          "value_type": "Bool",
          "takes_value": false,
          "description": "print the version number and exit.",
          "multiple": false,
          "conflicts_with": [],
          "requires": []
        },
        {
          "short": "-F",
          "long": null,
          "value_type": "Bool",
          "takes_value": false,
          "description": "force writing or rewriting of the archive; ignored with the -n or -m options, or if this is a subexperiment.",
          "multiple": false,
          "conflicts_with": [],
          "requires": []
        },
        {
          "short": "-a",
          "long": null,
          "value_type": "Bool",
          "takes_value": false,
          "description": "specify archiving of binaries and other files; in addition to disable this feature (off), or enable archiving off all loadobjects and sources (on), the other options support a more refined selection. All of these options enable archiving, but the keyword controls what exactly is selected: all load objects (ldobjects), all source files (src), the loadobjects asscoiated with a program counter (usedldobjects), or the source files associated with a program counter (usedsrc); the default is \"-a ldobjects\".",
          "multiple": false,
          "conflicts_with": [],
          "requires": []
        },
        {
          "short": "-d",
          "long": null,
          "value_type": "File",
          "takes_value": true,
          "description": "specifies the location of a common archive; this is a directory that contains archived files.",
          "multiple": false,
          "conflicts_with": [],
          "requires": []
        },
        {
          "short": "-m",
          "long": null,
          "value_type": "File",
          "takes_value": true,
          "description": "archive only those source, object, and debug info files whose full path name matches the given POSIX compliant regular expression.",
          "multiple": false,
          "conflicts_with": [],
          "requires": []
        },
        {
          "short": "-n",
          "long": null,
          "value_type": "Bool",
          "takes_value": false,
          "description": "archive the named experiment only, not any of its descendants.",
          "multiple": false,
          "conflicts_with": [],
          "requires": []
        },
        {
          "short": "-q",
          "long": null,
          "value_type": "Bool",
          "takes_value": false,
          "description": "do not write any warnings to stderr; messages are archived and can be retrieved later.",
          "multiple": false,
          "conflicts_with": [],
          "requires": []
        }
      ],
      "positional": [
        {
          "name": "EXPERIMENT",
          "value_type": "String",
          "required": true,
          "multiple": false,
          "description": null
        }
      ],
      "subcommands": [],
      "aliases": []
    }
  ],
  "positional": [
    {
      "name": "action",
      "value_type": "String",
      "required": true,
      "multiple": false,
      "description": null
    },
    {
      "name": "qualifier",
      "value_type": "String",
      "required": false,
      "multiple": false,
      "description": null
    },
    {
      "name": "target",
      "value_type": "String",
      "required": true,
      "multiple": false,
      "description": null
    }
  ],
  "source": "Merged",
  "confidence": 1.0,
  "version": null
}